satellite_parser/__init__.py
satellite_parser/base.py
satellite_parser/constants.py
satellite_parser/gf1.py
satellite_parser/gf1b.py
satellite_parser/gf1c.py
satellite_parser/gf1d.py
satellite_parser/gf2.py
satellite_parser/gf3.py
satellite_parser/gf4.py
satellite_parser/gf5.py
satellite_parser/gf6.py
satellite_parser/gf7.py
satellite_parser/sv101.py
satellite_parser/sv102.py
satellite_parser/sv103.py
satellite_parser/sv104.py
satellite_parser-0.2.5.dist-info/LICENSE
satellite_parser-0.2.5.dist-info/METADATA
satellite_parser-0.2.5.dist-info/WHEEL
satellite_parser-0.2.5.dist-info/top_level.txt
satellite_parser-0.2.5.dist-info/RECORD
