Metadata-Version: 2.1
Name: satellite-parser
Version: 0.2.5
Summary: parsing origin data of remote sensor satellites
Home-page: https://github.com/chinesejar/satellite-parser
Author: chinesejar
Author-email: chinesejar@gmail.com
License: UNKNOWN
Project-URL: Bug Tracker, https://github.com/chinesejar/satellite-parser/issues
Platform: UNKNOWN
Classifier: Programming Language :: Python :: 3
Classifier: License :: OSI Approved :: MIT License
Classifier: Operating System :: OS Independent
Requires-Python: >=3.6
License-File: LICENSE
Requires-Dist: xmltodict (>=0.12.0)
